outgoing/__init__.py
outgoing/__main__.py
outgoing/config.py
outgoing/core.py
outgoing/errors.py
outgoing/passwords.py
outgoing/py.typed
outgoing/util.py
outgoing/senders/__init__.py
outgoing/senders/command.py
outgoing/senders/mailboxes.py
outgoing/senders/null.py
outgoing/senders/smtp.py
outgoing-0.6.3.dist-info/METADATA
outgoing-0.6.3.dist-info/WHEEL
outgoing-0.6.3.dist-info/entry_points.txt
outgoing-0.6.3.dist-info/licenses/LICENSE
outgoing-0.6.3.dist-info/RECORD
