Metadata-Version: 2.4
Name: outgoing
Version: 0.6.3
Summary: Common interface for multiple e-mail methods
Project-URL: Source Code, https://github.com/jwodder/outgoing
Project-URL: Bug Tracker, https://github.com/jwodder/outgoing/issues
Project-URL: Documentation, https://outgoing.readthedocs.io
Author-email: John Thorvald Wodder II <outgoing@varonathe.org>
License-Expression: MIT
License-File: LICENSE
Keywords: e-mail,email,mailbox,mbox,send mail,sendmail,smtp
Classifier: Intended Audience :: Developers
Classifier: Intended Audience :: Information Technology
Classifier: Intended Audience :: System Administrators
Classifier: Programming Language :: Python :: 3
Classifier: Programming Language :: Python :: 3 :: Only
Classifier: Programming Language :: Python :: 3.10
Classifier: Programming Language :: Python :: 3.11
Classifier: Programming Language :: Python :: 3.12
Classifier: Programming Language :: Python :: 3.13
Classifier: Programming Language :: Python :: 3.14
Classifier: Programming Language :: Python :: Implementation :: CPython
Classifier: Programming Language :: Python :: Implementation :: PyPy
Classifier: Topic :: Communications :: Email
Classifier: Typing :: Typed
Requires-Python: >=3.10
Requires-Dist: keyring>=21.7
Requires-Dist: morecontext~=0.4
Requires-Dist: platformdirs<5.0,>=3.0
Requires-Dist: pydantic~=2.0
Requires-Dist: python-dotenv<2.0,>=0.11
Requires-Dist: tomli<3.0,>=1.2; python_version < '3.11'
